agent_runtime_framework/__init__.py
agent_runtime_framework/adapters/__init__.py
agent_runtime_framework/adapters/django.py
agent_runtime_framework/agents/__init__.py
agent_runtime_framework/agents/base.py
agent_runtime_framework/agents/journey.py
agent_runtime_framework/executor/__init__.py
agent_runtime_framework/executor/hooks.py
agent_runtime_framework/executor/loop.py
agent_runtime_framework/memory/__init__.py
agent_runtime_framework/memory/context.py
agent_runtime_framework/memory/store.py
agent_runtime_framework/prompts/__init__.py
agent_runtime_framework/prompts/manager.py
agent_runtime_framework/router/__init__.py
agent_runtime_framework/router/intent.py
agent_runtime_framework/state/__init__.py
agent_runtime_framework/state/base.py
agent_runtime_framework/tools/__init__.py
agent_runtime_framework/tools/base.py
agent_runtime_framework/tools/schema.py
agent_runtime_framework-0.1.0.dist-info/METADATA
agent_runtime_framework-0.1.0.dist-info/WHEEL
agent_runtime_framework-0.1.0.dist-info/top_level.txt
agent_runtime_framework-0.1.0.dist-info/RECORD
